justkeydding/__init__.py
justkeydding/__main__.py
justkeydding/__version__.py
justkeydding/cli.py
justkeydding/dataset.py
justkeydding/dataset_creator.py
justkeydding/ga.py
justkeydding/justkeydding_ensemble.py
justkeydding/model_tester.py
justkeydding/model_trainer.py
justkeydding/inputs/__init__.py
justkeydding/inputs/audio.py
justkeydding/inputs/midi.py
justkeydding/inputs/symbolic.py
justkeydding/optimizer/__init__.py
justkeydding/optimizer/ensembler.py
justkeydding/optimizer/evaluator.py
justkeydding/optimizer/evolver.py
justkeydding/optimizer/generator.py
justkeydding/parameters/__init__.py
justkeydding/parameters/key_profiles.py
justkeydding/parameters/key_transitions.py
justkeydding/parameters/observations.py
justkeydding/tools/__init__.py
justkeydding/tools/evaluation.py
justkeydding-1.12.3.dist-info/LICENSE
justkeydding-1.12.3.dist-info/METADATA
justkeydding-1.12.3.dist-info/WHEEL
justkeydding-1.12.3.dist-info/top_level.txt
justkeydding-1.12.3.dist-info/RECORD
